.travis.yml
README.rst
bootstrap.py
buildout.cfg
setup.py
travis.cfg
docs/HISTORY.rst
docs/INSTALL.txt
docs/LICENSE.GPL
docs/LICENSE.txt
quintagroup/__init__.py
quintagroup.substyle.egg-info/PKG-INFO
quintagroup.substyle.egg-info/SOURCES.txt
quintagroup.substyle.egg-info/dependency_links.txt
quintagroup.substyle.egg-info/entry_points.txt
quintagroup.substyle.egg-info/namespace_packages.txt
quintagroup.substyle.egg-info/not-zip-safe
quintagroup.substyle.egg-info/requires.txt
quintagroup.substyle.egg-info/top_level.txt
quintagroup/substyle/__init__.py
quintagroup/substyle/configure.zcml
quintagroup/substyle/tests.py
quintagroup/substyle/browser/__init__.py
quintagroup/substyle/browser/configure.zcml
quintagroup/substyle/browser/folder.py
quintagroup/substyle/profiles/default/actions.xml
quintagroup/substyle/profiles/default/cssregistry.xml
quintagroup/substyle/profiles/default/metadata.xml