Metadata-Version: 1.0
Name: quintagroup.substyle
Version: 1.3
Summary: Styles for site subsections
Home-page: https://github.com/quintagroup/quintagroup.substyle
Author: Quintagroup
Author-email: support@quintagroup.com
License: GPL
Keywords: site styles sections subsections
Platform: UNKNOWN
Classifier: Framework :: Plone
Classifier: Framework :: Plone :: 3.3
Classifier: Framework :: Plone :: 4.0
Classifier: Framework :: Plone :: 4.1
Classifier: Framework :: Plone :: 4.2
Classifier: Framework :: Plone :: 4.3
Classifier: Programming Language :: Python
Classifier: Development Status :: 5 - Production/Stable
Classifier: Environment :: Plugins
Classifier: Intended Audience :: Developers
Classifier: Natural Language :: English
Classifier: Operating System :: OS Independent
Classifier: Programming Language :: Python
Classifier: License :: OSI Approved :: GNU General Public License (GPL)
